spider_xhs_lc/__init__.py
spider_xhs_lc/server.py
spider_xhs_lc-0.1.1.dist-info/METADATA
spider_xhs_lc-0.1.1.dist-info/WHEEL
spider_xhs_lc-0.1.1.dist-info/entry_points.txt
spider_xhs_lc-0.1.1.dist-info/top_level.txt
spider_xhs_lc-0.1.1.dist-info/RECORD
